color_ur_text/__init__.py
color_ur_text/colored_text.py
color_ur_text-0.1.3.1.dist-info/licenses/LICENSE.txt
color_ur_text-0.1.3.1.dist-info/METADATA
color_ur_text-0.1.3.1.dist-info/WHEEL
color_ur_text-0.1.3.1.dist-info/top_level.txt
color_ur_text-0.1.3.1.dist-info/RECORD
