Metadata-Version: 2.4
Name: color_ur_text
Version: 0.1.3.1
Summary: A module for printing colored text to terminal/console in Python, Now with more methods and colors like displayiing animations. refer to the README.md
Author-email: Basit Ahmad Ganie <basitahmed1412@gmail.com>
License: MIT
Project-URL: github page, https://github.com/basitganie/colored_text
Keywords: text-color,ANSI,terminal,python-color
Classifier: Programming Language :: Python :: 3
Classifier: License :: OSI Approved :: MIT License
Classifier: Operating System :: OS Independent
Requires-Python: >=3.0
License-File: LICENSE.txt
Dynamic: license-file
